Workbook

Sheet Report
D2: Select Vehicle Variant
D3: MAXX CITY 1.3 LX BS6.2
B5: Vehicle Price | C5: Ex-Showroom Price | D5: =IFERROR(VLOOKUP($D$3,Sheet1!$B$2:$R$46,MATCH(Report!$C5,Sheet1!$B$2:$R$2,0),0),"") -> 793501 | F5: Sr. | G5: Points
C6: TCS | D6: =IFERROR(VLOOKUP($D$3,Sheet1!$B$2:$R$46,MATCH(Report!$C6,Sheet1!$B$2:$R$2,0),0),"") -> 0 | F6: 1 | G6: Insurance is mandatory for vehicles older than 90 days.
C7: Comprehensive + Zero Dep. Insurance | D7: =IFERROR(VLOOKUP($D$3,Sheet1!$B$2:$R$46,MATCH(Report!$C7,Sheet1!$B$2:$R$2,0),0),"") -> 46664 | F7: 2 | G7: Out-of-territory vehicles will be kept out of the cartel.
C8: R.T.O. Charges With Hypo. | D8: =IFERROR(VLOOKUP($D$3,Sheet1!$B$2:$R$46,MATCH(Report!$C8,Sheet1!$B$2:$R$2,0),0),"") -> 42648 | F8: 3 | G8: Insurance is mandatory for all vehicles with a 2025 VIN.
C9: RSA (Road Side Assistance) For 1 Year | D9: =IFERROR(VLOOKUP($D$3,Sheet1!$B$2:$R$46,MATCH(Report!$C9,Sheet1!$B$2:$R$2,0),0),"") -> 1519 | F9: 4 | G9: VIN 25 vehicles will remain out of cartel
C10: SMC Road - Tax (If Applicable) | D10: =IFERROR(VLOOKUP($D$3,Sheet1!$B$2:$R$46,MATCH(Report!$C10,Sheet1!$B$2:$R$2,0),0),"") -> 19838 | F10: 5 | G10: An accessories package worth ₹12,000 will be mandatory.
C11: MAXI CARE | D11: =IFERROR(VLOOKUP($D$3,Sheet1!$B$2:$R$46,MATCH(Report!$C11,Sheet1!$B$2:$R$2,0),0),"") -> 3500 | F11: 6 | G11: There is no discount on accessories package
C12: Accessories | D12: =IFERROR(VLOOKUP($D$3,Sheet1!$B$2:$R$46,MATCH(Report!$C12,Sheet1!$B$2:$R$2,0),0),"") -> 12000 | F12: 7 | G12: As per price list insurance is mandatory
C13: ON ROAD PRICE With SMC Road Tax | D13: =IFERROR(VLOOKUP($D$3,Sheet1!$B$2:$R$46,MATCH(Report!$C13,Sheet1!$B$2:$R$2,0),0),"") -> 919670 | F13: 8 | G13: Price will remain the same at both dealerships
C14: ON ROAD PRICE Without SMC Road Tax | D14: =IFERROR(VLOOKUP($D$3,Sheet1!$B$2:$R$46,MATCH(Report!$C14,Sheet1!$B$2:$R$2,0),0),"") -> 899832 | F14: 9 | G14: NO Business with DSA Sales
B15: VIN 2026 | C15: Total M&M Scheme with GST (2026) | D15: =IFERROR(VLOOKUP($D$3,Sheet1!$B$2:$R$46,MATCH(Report!$C15,Sheet1!$B$2:$R$2,0),0),"") -> 45000 | F15: 10 | G15: Invoice on full amount
C16: VIN 2026 Dealer Offer | D16: =IFERROR(VLOOKUP($D$3,Sheet1!$B$2:$R$46,MATCH(Report!$C16,Sheet1!$B$2:$R$2,0),0),"") -> 50K + RSA FREE | F16: 11 | G16: Only bulk deals of 10 or more vehicles will be considered outside the cartel
B17: VIN 2025 | C17: M&M Scheme with GST (2025) | D17: =IFERROR(VLOOKUP($D$3,Sheet1!$B$2:$R$46,MATCH(Report!$C17,Sheet1!$B$2:$R$2,0),0),"")
C18: Dealer Contribution with GST (2025) | D18: =IFERROR(VLOOKUP($D$3,Sheet1!$B$2:$R$46,MATCH(Report!$C18,Sheet1!$B$2:$R$2,0),0),"")
C19: Total Scheme with GST (M&M + Dealer) (2025) | D19: =IFERROR(VLOOKUP($D$3,Sheet1!$B$2:$R$46,MATCH(Report!$C19,Sheet1!$B$2:$R$2,0),0),"")
C20: VIN 2025 Dealer Offer | D20: =IFERROR(VLOOKUP($D$3,Sheet1!$B$2:$R$46,MATCH(Report!$C20,Sheet1!$B$2:$R$2,0),0),"")
B21: Other Offers | C21: Exchange Bonus | D21: =IFERROR(VLOOKUP($D$3,Sheet1!$B$2:$R$46,MATCH(Report!$C21,Sheet1!$B$2:$R$2,0),0),"") -> 35000
C22: Scrappage Bonus | D22: =IFERROR(VLOOKUP($D$3,Sheet1!$B$2:$R$46,MATCH(Report!$C22,Sheet1!$B$2:$R$2,0),0),"") -> 45000

Sheet Sheet1
A1: MODEL & VARIANT | C1: VEHICLE PRICE | M1: JUNE-2026 - VIN 2026 | O1: Other Offers
A2: Model Name | B2: Variant | C2: Ex-Showroom Price | D2: TCS | E2: Comprehensive + Zero Dep. Insurance | F2: R.T.O. Charges With Hypo. | G2: RSA (Road Side Assistance) For 1 Year | H2: SMC Road - Tax (If Applicable) | I2: MAXI CARE | J2: Accessories | K2: ON ROAD PRICE With SMC Road Tax | L2: ON ROAD PRICE Without SMC Road Tax | M2: Total M&M Scheme with GST (2026) | N2: VIN 2026 Dealer Offer | O2: Exchange Bonus | P2: Scrappage Bonus
A3: BOL MAXX PUP CITY 1.3 LXD | B3: MAXX CITY 1.3 LX BS6.2 | C3: 793501 | D3: 0 | E3: 46664 | F3: 42648 | G3: 1519 | H3: 19838 | I3: 3500 | J3: 12000 | K3: =SUM(C3:J3) -> 919670 | L3: =K3-H3 -> 899832 | M3: 45000 | N3: 50K + RSA FREE | O3: 35000 | P3: 45000
A4: BOL MAXX PUP CITY 1.3 LXD CBC | B4: MAXX CITY 1.3 LX CBC BS6.2 | C4: 784501 | D4: 0 | E4: 46371 | F4: 43290 | G4: 1519 | H4: 19613 | I4: 3500 | J4: 12000 | K4: =SUM(C4:J4) -> 910794 | L4: =K4-H4 -> 891181 | M4: 45000 | N4: 50K + RSA FREE | O4: 35000 | P4: 45000
A5: BOL MAXX PUP CITY 1.3 MXD | B5: MAXX CITY 1.3 MXi BS6.2 | C5: 822501 | D5: 0 | E5: 47817 | F5: 44122 | G5: 1519 | H5: 20563 | I5: 3500 | J5: 12000 | K5: =SUM(C5:J5) -> 952022 | L5: =K5-H5 -> 931459 | M5: 45000 | N5: 50K + RSA FREE | O5: 35000 | P5: 45000
A6: BOL MAXX PUP CITY 1.3 SXI AC | B6: MAXX CITY 1.3 SXi AC - BS6.2 | C6: 816500 | D6: 0 | E6: 47412 | F6: 43817 | G6: 1519 | H6: 20413 | I6: 3500 | J6: 12000 | K6: =SUM(C6:J6) -> 945161 | L6: =K6-H6 -> 924748 | M6: 33000 | N6: 33K + RSA FREE | O6: 35000 | P6: 45000
A7: BOL MAXX PUP CITY 1.3 VXID AC | B7: MAXX CITY 1.3 VXi AC - BS6.2 | C7: 835500 | D7: 0 | E7: 48395 | F7: 44783 | G7: 1519 | H7: 20888 | I7: 3500 | J7: 12000 | K7: =SUM(C7:J7) -> 966585 | L7: =K7-H7 -> 945697 | M7: 33000 | N7: 33K + RSA FREE | O7: 35000 | P7: 45000
A8: BOL MAXX PUP CITY LX CNG | B8: MAXX CITY LX CNG BS6.2 | C8: 816501 | D8: 0 | E8: 47412 | F8: 43817 | G8: 1519 | H8: 12248 | I8: 3500 | J8: 12000 | K8: =SUM(C8:J8) -> 936997 | L8: =K8-H8 -> 924749 | M8: 63000 | N8: 63K + RSA FREE | O8: 35000 | P8: 45000
A9: BOL MAXX PUP HD 1.3 LX | B9: MAXX HD 1.3 LX BS6.2 | C9: 943499 | D9: 0 | E9: 51559 | F9: 50275 | G9: 1519 | H9: 23587 | I9: 3500 | J9: 12000 | K9: =SUM(C9:J9) -> 1085939 | L9: =K9-H9 -> 1062352 | M9: 8000 | N9: 8K + RSA FREE | O9: 35000 | P9: 45000
A10: BOL MAXX PUP HD 1.3 VXID AC | B10: MAXX HD 1.3 VXi AC - BS6.2 | C10: 992501 | D10: 0 | E10: 53156 | F10: 52766 | G10: 1519 | H10: 24813 | I10: 3500 | J10: 12000 | K10: =SUM(C10:J10) -> 1140255 | L10: =K10-H10 -> 1115442 | M10: 8000 | N10: 8K + RSA FREE | O10: 35000 | P10: 45000
A11: BOL MAXX PUP HD 1.7 LX | B11: MAXX HD 1.7 LX BS6.2 | C11: 953500 | D11: 0 | E11: 51886 | F11: 51133 | G11: 1519 | H11: 23838 | I11: 3500 | J11: 12000 | K11: =SUM(C11:J11) -> 1097376 | L11: =K11-H11 -> 1073538 | M11: 18000 | N11: 30K + RSA FREE | O11: 35000 | P11: 45000
A12: BOL MAXX PUP HD 1.7 LX CBC | B12: MAXX HD 1.7 LX CBC BS6.2 | C12: 929500 | D12: 0 | E12: 51104 | F12: 51013 | G12: 1519 | H12: 23238 | I12: 3500 | J12: 12000 | K12: =SUM(C12:J12) -> 1071874 | L12: =K12-H12 -> 1048636 | M12: 18000 | N12: 30K + RSA FREE | O12: 35000 | P12: 45000
A13: BOL MAXX PUP HD 1.7 MX | B13: MAXX HD 1.7 MXi BS6.2 | C13: 984500 | D13: 0 | E13: 52897 | F13: 52709 | G13: 1519 | H13: 24613 | I13: 3500 | J13: 12000 | K13: =SUM(C13:J13) -> 1131738 | L13: =K13-H13 -> 1107125 | M13: 8000 | N13: 8K + RSA FREE | O13: 35000 | P13: 45000
A14: BOL MAXX PUP HD 1.7 VXI AC | B14: MAXX HD 1.7 VXi AC - BS6.2 | C14: 999499 | D14: 0 | E14: 53393 | F14: 53472 | G14: 1519 | H14: 24987 | I14: 3500 | J14: 12000 | K14: =SUM(C14:J14) -> 1148370 | L14: =K14-H14 -> 1123383 | M14: 18000 | N14: 18K + RSA FREE | O14: 35000 | P14: 45000
... A38: BOLERO CAMPER 4WD PSD RXD - Refresh | B38: BOL CAMPER GOLD RXD 4WD BS6.2 - Refresh | C38: 1062501 | D38: 10625 | E38: 55446 | F38: 56325 | G38: 1519 | H38: 37188 | I38: 3500 | J38: 12000 | K38: =SUM(C38:J38) -> 1239104 | L38: =K38-H38 -> 1201916 | M38: 13000 | N38: 13K + RSA FREE | O38: 35000 | P38: 45000

Sheet MasterData
A1: Variant | C1: Data Validation Prep. | E1: =VLOOKUP(A3,'[CV Price List D. 03.06.2026.xlsx]Price List'!$B$1:$L$40,{2,3,4,5,6,7,8},FALSE)
A2: MAXX CITY 1.3 LX BS6.2 | C2: {=TRANSPOSE(_xlfn._xlws.SORT(_xlfn._xlws.FILTER(Vehicle_Model[Variant],ISNUMBER(SEARCH(Report!D3,Vehicle_Model[Variant])),"Not Found")))} -> MAXX CITY 1.3 LX BS6.2
A3: MAXX CITY 1.3 LX CBC BS6.2
A4: MAXX CITY 1.3 MXi BS6.2
A5: MAXX CITY 1.3 SXi AC - BS6.2
A6: MAXX CITY 1.3 VXi AC - BS6.2
A7: MAXX CITY LX CNG BS6.2
A8: MAXX HD 1.3 LX BS6.2
A9: MAXX HD 1.3 VXi AC - BS6.2
A10: MAXX HD 1.7 LX BS6.2
A11: MAXX HD 1.7 LX CBC BS6.2
A12: MAXX HD 1.7 MXi BS6.2
A13: MAXX HD 1.7 VXi AC - BS6.2
A14: MAXX HD 1.7 VXi BS6.2
... A37: BOL CAMPER GOLD RXD 4WD BS6.2 - Refresh
