Workbook

Sheet Report
D2: Select Vehicle Variant
D3: MAXX CITY 1.3 LX BS6.2
B5: Vehicle Price | C5: Ex-Showroom Price | D5: =IFERROR(VLOOKUP($D$3,Sheet1!$B$2:$Z$45,MATCH(Report!$C5,Sheet1!$B$2:$Z$2,0),0),"") -> 772700 | F5: Sr. | G5: Points
C6: TCS | D6: =IFERROR(VLOOKUP($D$3,Sheet1!$B$2:$Z$45,MATCH(Report!$C6,Sheet1!$B$2:$Z$2,0),0),"") -> 0 | F6: 1 | G6: As per price list insurance is mandatory
C7: Comprehensive + Zero Dep. Insurance | D7: =IFERROR(VLOOKUP($D$3,Sheet1!$B$2:$Z$45,MATCH(Report!$C7,Sheet1!$B$2:$Z$2,0),0),"") -> 46940 | F7: 2 | G7: There is no discount on accessories package
C8: R.T.O. Charges With Hypo. | D8: =IFERROR(VLOOKUP($D$3,Sheet1!$B$2:$Z$45,MATCH(Report!$C8,Sheet1!$B$2:$Z$2,0),0),"") -> 41590 | F8: 3 | G8: Price will remain the same at both showrooms
C9: RSA (Road Side Assistance) For 1 Year | D9: =IFERROR(VLOOKUP($D$3,Sheet1!$B$2:$Z$45,MATCH(Report!$C9,Sheet1!$B$2:$Z$2,0),0),"") -> 1519 | F9: 4 | G9: For vehicles where the accessories package is not free, an accessories package worth ₹12,000 will be mandatory.
C10: SMC Road - Tax (If Applicable) | D10: =IFERROR(VLOOKUP($D$3,Sheet1!$B$2:$Z$45,MATCH(Report!$C10,Sheet1!$B$2:$Z$2,0),0),"") -> 19318 | F10: 5 | G10: NO Additional Payout to be Passed on to DSA - Both PV & CV
C11: MAXI CARE | D11: =IFERROR(VLOOKUP($D$3,Sheet1!$B$2:$Z$45,MATCH(Report!$C11,Sheet1!$B$2:$Z$2,0),0),"") -> 3500 | F11: 6 | G11: NO DSA Sale on Exshowroom
C12: Accessories | D12: =IFERROR(VLOOKUP($D$3,Sheet1!$B$2:$Z$45,MATCH(Report!$C12,Sheet1!$B$2:$Z$2,0),0),"") -> 12000 | F12: 7 | G12: Invoice on full amount
C13: ON ROAD PRICE With SMC Road Tax | D13: =IFERROR(VLOOKUP($D$3,Sheet1!$B$2:$Z$45,MATCH(Report!$C13,Sheet1!$B$2:$Z$2,0),0),"") -> 897566 | F13: 8 | G13: For Camper Model Insurance in house is mandatory and in case of out house Insurance only M&M Consumer offer will be applicable
C14: ON ROAD PRICE Without SMC Road Tax | D14: =IFERROR(VLOOKUP($D$3,Sheet1!$B$2:$Z$45,MATCH(Report!$C14,Sheet1!$B$2:$Z$2,0),0),"") -> 878249 | F14: 9 | G14: Only bulk deals of 10 or more vehicles will be considered outside the cartel
B15: VIN 2026 | C15: Total M&M Scheme with GST (2026) | D15: =IFERROR(VLOOKUP($D$3,Sheet1!$B$2:$Z$45,MATCH(Report!$C15,Sheet1!$B$2:$Z$2,0),0),"") -> 30000 | F15: 10 | G15: Vin's Above 90 Days are open for Discount - Auditor to take Tally Stock on 5th of Every month for >90 Days Stock
C16: VIN 2026 Dealer Offer | D16: =IFERROR(VLOOKUP($D$3,Sheet1!$B$2:$Z$45,MATCH(Report!$C16,Sheet1!$B$2:$Z$2,0),0),"") -> 0 | F16: 11 | G16: VIN 2024 vehicles are not part of Discount adherance
B17: VIN 2025 | C17: M&M Scheme with GST (2025) | D17: =IFERROR(VLOOKUP($D$3,Sheet1!$B$2:$Z$45,MATCH(Report!$C17,Sheet1!$B$2:$Z$2,0),0),"") -> 38000
C18: Dealer Contribution with GST (2025) | D18: =IFERROR(VLOOKUP($D$3,Sheet1!$B$2:$Z$45,MATCH(Report!$C18,Sheet1!$B$2:$Z$2,0),0),"") -> 10000
C19: Total Scheme with GST (M&M + Dealer) (2025) | D19: =IFERROR(VLOOKUP($D$3,Sheet1!$B$2:$Z$45,MATCH(Report!$C19,Sheet1!$B$2:$Z$2,0),0),"") -> 48000
C20: VIN 2025 Dealer Offer | D20: =IFERROR(VLOOKUP($D$3,Sheet1!$B$2:$Z$45,MATCH(Report!$C20,Sheet1!$B$2:$Z$2,0),0),"") -> 100% Insurance + 12K Accessories + RSA FREE
B21: Other Offers | C21: Exchange Bonus | D21: =IFERROR(VLOOKUP($D$3,Sheet1!$B$2:$Z$45,MATCH(Report!$C21,Sheet1!$B$2:$Z$2,0),0),"") -> 35000
C22: Scrappage Bonus | D22: =IFERROR(VLOOKUP($D$3,Sheet1!$B$2:$Z$45,MATCH(Report!$C22,Sheet1!$B$2:$Z$2,0),0),"") -> 45000

Sheet Sheet1
A1: MODEL & VARIANT | C1: VEHICLE PRICE | M1: JAN-2026 VIN 2026 | O1: JAN-2026 VIN 2025
A2: Model Name | B2: Variant | C2: Ex-Showroom Price | D2: TCS | E2: Comprehensive + Zero Dep. Insurance | F2: R.T.O. Charges With Hypo. | G2: RSA (Road Side Assistance) For 1 Year | H2: SMC Road - Tax (If Applicable) | I2: MAXI CARE | J2: Accessories | K2: ON ROAD PRICE With SMC Road Tax | L2: ON ROAD PRICE Without SMC Road Tax | M2: Total M&M Scheme with GST (2026) | N2: VIN 2026 Dealer Offer | O2: M&M Scheme with GST (2025) | P2: Dealer Contribution with GST (2025) | Q2: Total Scheme with GST (M&M + Dealer) (2025) | R2: VIN 2025 Dealer Offer | T2: Exchange Bonus | U2: Scrappage Bonus
A3: BOL MAXX PUP CITY 1.3 LX | B3: MAXX CITY 1.3 LX BS6.2 | C3: {=VLOOKUP(A3,[1]Sheet1!$B$1:$L$35,{2,3,4,5,6,7,8,9,10,11},FALSE)} -> 772700 | D3: 0 | E3: 46940 | F3: 41590 | G3: 1519 | H3: 19318 | I3: 3500 | J3: 12000 | K3: 897566 | L3: 878249 | M3: =VLOOKUP(B3,'[2]Consumer Scheme 08.01.2026'!$B$2:$I$370,3,FALSE) -> 30000 | O3: {=VLOOKUP(B3,'[2]Consumer Scheme 08.01.2026'!$B$2:$I$370,{6,7,8},FALSE)} -> 38000 | P3: 10000 | Q3: 48000 | R3: 100% Insurance + 12K Accessories + RSA FREE | T3: 35000 | U3: 45000
A4: BOL MAXX PUP CITY 1.3 LX CBC | B4: MAXX CITY 1.3 LX CBC BS6.2 | C4: {=VLOOKUP(A4,[1]Sheet1!$B$1:$L$35,{2,3,4,5,6,7,8,9,10,11},FALSE)} -> 763499 | D4: 0 | E4: 46629 | F4: 41722 | G4: 1519 | H4: 19087 | I4: 3500 | J4: 12000 | K4: 887957 | L4: 868869 | M4: =VLOOKUP(B4,'[2]Consumer Scheme 08.01.2026'!$B$2:$I$370,3,FALSE) -> 30000 | O4: {=VLOOKUP(B4,'[2]Consumer Scheme 08.01.2026'!$B$2:$I$370,{6,7,8},FALSE)} -> 38000 | P4: 10000 | Q4: 48000 | R4: 100% Insurance + 12K Accessories + RSA FREE | T4: 35000 | U4: 45000
A5: BOL MAXX PUP CITY 1.3 MXD | B5: MAXX CITY 1.3 MXi BS6.2 | C5: {=VLOOKUP(A5,[1]Sheet1!$B$1:$L$35,{2,3,4,5,6,7,8,9,10,11},FALSE)} -> 795600 | D5: 0 | E5: 47715 | F5: 42754 | G5: 1519 | H5: 19890 | I5: 3500 | J5: 12000 | K5: 922978 | L5: 903088 | M5: =VLOOKUP(B5,'[2]Consumer Scheme 08.01.2026'!$B$2:$I$370,3,FALSE) -> 30000 | O5: {=VLOOKUP(B5,'[2]Consumer Scheme 08.01.2026'!$B$2:$I$370,{6,7,8},FALSE)} -> 38000 | P5: 10000 | Q5: 48000 | R5: 100% Insurance + 12K Accessories + RSA FREE | T5: 35000 | U5: 45000
A6: BOL MAXX PUP CITY 1.3 SXI AC | B6: MAXX CITY 1.3 SXi AC - BS6.2 | C6: {=VLOOKUP(A6,[1]Sheet1!$B$1:$L$35,{2,3,4,5,6,7,8,9,10,11},FALSE)} -> 800199 | D6: 0 | E6: 47869 | F6: 42988 | G6: 1519 | H6: 20005 | I6: 3500 | J6: 12000 | K6: 928080 | L6: 908075 | M6: =VLOOKUP(B6,'[2]Consumer Scheme 08.01.2026'!$B$2:$I$370,3,FALSE) -> 30000 | O6: {=VLOOKUP(B6,'[2]Consumer Scheme 08.01.2026'!$B$2:$I$370,{6,7,8},FALSE)} -> 38000 | P6: 10000 | Q6: 48000 | R6: 100% Insurance + 12K Accessories + RSA FREE | T6: 35000 | U6: 45000
A7: BOL MAXX PUP CITY 1.3 VXID AC | B7: MAXX CITY 1.3 VXi AC - BS6.2 | C7: {=VLOOKUP(A7,[1]Sheet1!$B$1:$L$35,{2,3,4,5,6,7,8,9,10,11},FALSE)} -> 809400 | D7: 0 | E7: 48178 | F7: 43456 | G7: 1519 | H7: 20235 | I7: 3500 | J7: 12000 | K7: 938288 | L7: 918053 | M7: =VLOOKUP(B7,'[2]Consumer Scheme 08.01.2026'!$B$2:$I$370,3,FALSE) -> 30000 | O7: {=VLOOKUP(B7,'[2]Consumer Scheme 08.01.2026'!$B$2:$I$370,{6,7,8},FALSE)} -> 38000 | P7: 10000 | Q7: 48000 | R7: 100% Insurance + 12K Accessories + RSA FREE | T7: 35000 | U7: 45000
A8: BOL MAXX PUP CITY 1.3 VXID | B8: MAXX CITY 1.3 VXi BS6.2 | C8: {=VLOOKUP(A8,[1]Sheet1!$B$1:$L$35,{2,3,4,5,6,7,8,9,10,11},FALSE)} -> 791000 | D8: 0 | E8: 47343 | F8: 42520 | G8: 1519 | H8: 19775 | I8: 3500 | J8: 12000 | K8: 917657 | L8: 897882 | M8: =VLOOKUP(B8,'[2]Consumer Scheme 08.01.2026'!$B$2:$I$370,3,FALSE) -> 30000 | O8: {=VLOOKUP(B8,'[2]Consumer Scheme 08.01.2026'!$B$2:$I$370,{6,7,8},FALSE)} -> 38000 | P8: 10000 | Q8: 48000 | R8: 100% Insurance + 12K Accessories + RSA FREE | T8: 35000 | U8: 45000
A9: BOL MAXX PUP CITY LX CNG | B9: MAXX CITY LX CNG BS6.2 | C9: {=VLOOKUP(A9,[1]Sheet1!$B$1:$L$35,{2,3,4,5,6,7,8,9,10,11},FALSE)} -> 793900 | D9: 0 | E9: 47658 | F9: 42668 | G9: 1519 | H9: 11908 | I9: 3500 | J9: 12000 | K9: 913153 | L9: 901245 | M9: =VLOOKUP(B9,'[2]Consumer Scheme 08.01.2026'!$B$2:$I$370,3,FALSE) -> 65000 | O9: {=VLOOKUP(B9,'[2]Consumer Scheme 08.01.2026'!$B$2:$I$370,{6,7,8},FALSE)} -> 65000 | P9: 10000 | Q9: 75000 | R9: 100% Insurance + 100% RTO + RSA FREE | T9: 35000 | U9: 45000
A10: BOL MAXX PUP HD 1.3 LX | B10: MAXX HD 1.3 LX BS6.2 | C10: {=VLOOKUP(A10,[1]Sheet1!$B$1:$L$35,{2,3,4,5,6,7,8,9,10,11},FALSE)} -> 916700 | D10: 0 | E10: 50714 | F10: 48912 | G10: 1519 | H10: 22918 | I10: 3500 | J10: 12000 | K10: 1056262 | L10: 1033345 | M10: =VLOOKUP(B10,'[2]Consumer Scheme 08.01.2026'!$B$2:$I$370,3,FALSE) -> 10000 | O10: {=VLOOKUP(B10,'[2]Consumer Scheme 08.01.2026'!$B$2:$I$370,{6,7,8},FALSE)} -> 23000 | P10: 5000 | Q10: 28000 | R10: MODEL NOT SPECIFIED | T10: 35000 | U10: 45000
A11: BOL MAXX PUP HD 1.3 VXID AC | B11: MAXX HD 1.3 VXi AC - BS6.2 | C11: {=VLOOKUP(A11,[1]Sheet1!$B$1:$L$35,{2,3,4,5,6,7,8,9,10,11},FALSE)} -> 962600 | D11: 0 | E11: 52213 | F11: 51246 | G11: 1519 | H11: 24065 | I11: 3500 | J11: 12000 | K11: 1107143 | L11: 1083078 | M11: =VLOOKUP(B11,'[2]Consumer Scheme 08.01.2026'!$B$2:$I$370,3,FALSE) -> 10000 | O11: {=VLOOKUP(B11,'[2]Consumer Scheme 08.01.2026'!$B$2:$I$370,{6,7,8},FALSE)} -> 28000 | P11: 5000 | Q11: 33000 | R11: MODEL NOT SPECIFIED | T11: 35000 | U11: 45000
A12: BOL MAXX PUP HD 1.7 LX | B12: MAXX HD 1.7 LX BS6.2 | C12: {=VLOOKUP(A12,[1]Sheet1!$B$1:$L$35,{2,3,4,5,6,7,8,9,10,11},FALSE)} -> 926900 | D12: 0 | E12: 51048 | F12: 49781 | G12: 1519 | H12: 23173 | I12: 3500 | J12: 12000 | K12: 1067920 | L12: 1044748 | M12: =VLOOKUP(B12,'[2]Consumer Scheme 08.01.2026'!$B$2:$I$370,3,FALSE) -> 20000 | O12: {=VLOOKUP(B12,'[2]Consumer Scheme 08.01.2026'!$B$2:$I$370,{6,7,8},FALSE)} -> 26000 | P12: 5000 | Q12: 31000 | R12: 30K + 17K Accessories + RSA FREE | T12: 35000 | U12: 45000
A13: BOL MAXX PUP HD 1.7 LX CBC | B13: MAXX HD 1.7 LX CBC BS6.2 | C13: {=VLOOKUP(A13,[1]Sheet1!$B$1:$L$35,{2,3,4,5,6,7,8,9,10,11},FALSE)} -> 902000 | D13: 0 | E13: 50233 | F13: 49114 | G13: 1519 | H13: 22550 | I13: 3500 | J13: 12000 | K13: 1040916 | L13: 1018366 | M13: =VLOOKUP(B13,'[2]Consumer Scheme 08.01.2026'!$B$2:$I$370,3,FALSE) -> 20000 | O13: {=VLOOKUP(B13,'[2]Consumer Scheme 08.01.2026'!$B$2:$I$370,{6,7,8},FALSE)} -> 26000 | P13: 5000 | Q13: 31000 | R13: 30K + 17K Accessories + RSA FREE | T13: 35000 | U13: 45000
A14: BOL MAXX PUP HD 1.7 MX | B14: MAXX HD 1.7 MXi BS6.2 | C14: {=VLOOKUP(A14,[1]Sheet1!$B$1:$L$35,{2,3,4,5,6,7,8,9,10,11},FALSE)} -> 954400 | D14: 0 | E14: 51947 | F14: 51179 | G14: 1519 | H14: 23860 | I14: 3500 | J14: 12000 | K14: 1098404 | L14: 1074544 | M14: =VLOOKUP(B14,'[2]Consumer Scheme 08.01.2026'!$B$2:$I$370,3,FALSE) -> 10000 | O14: {=VLOOKUP(B14,'[2]Consumer Scheme 08.01.2026'!$B$2:$I$370,{6,7,8},FALSE)} -> 35000 | P14: 5000 | Q14: 40000 | R14: 35K + 17K Accessories + RSA FREE | T14: 35000 | U14: 45000
... A36: BOL PIK UP FB 1.3T - BS6.2 - PS AC | B36: BOL PIK UP FB 1.3T - BS6.2 - PS AC | C36: {=VLOOKUP(A36,[1]Sheet1!$B$1:$L$35,{2,3,4,5,6,7,8,9,10,11},FALSE)} -> 985700 | D36: 0 | E36: 52969 | F36: 52420 | G36: 1519 | H36: 24643 | I36: 3500 | J36: 12000 | K36: 1132751 | L36: 1108109 | M36: =VLOOKUP(B36,'[2]Consumer Scheme 08.01.2026'!$B$2:$I$370,3,FALSE) -> 15000 | O36: {=VLOOKUP(B36,'[2]Consumer Scheme 08.01.2026'!$B$2:$I$370,{6,7,8},FALSE)} -> 23000 | P36: 5000 | Q36: 28000 | R36: 23K + 12K Accessories + RSA FREE | T36: 35000 | U36: 45000

Sheet MasterData
A1: Variant | C1: Data Validation Prep. | E1: =VLOOKUP(A3,'[CV Price List D. 09.01.2026.xlsx]Sheet1'!$B$1:$L$35,{2,3,4,5,6,7,8,9,10,11},FALSE)
A2: MAXX CITY 1.3 LX BS6.2 | C2: {=TRANSPOSE(_xlfn._xlws.SORT(_xlfn._xlws.FILTER(Vehicle_Model[Variant],ISNUMBER(SEARCH(Report!D3,Vehicle_Model[Variant])),"Not Found")))} -> MAXX CITY 1.3 LX BS6.2
A3: MAXX CITY 1.3 LX CBC BS6.2
A4: MAXX CITY 1.3 MXi BS6.2
A5: MAXX CITY 1.3 SXi AC - BS6.2
A6: MAXX CITY 1.3 VXi AC - BS6.2
A7: MAXX CITY 1.3 VXi BS6.2
A8: MAXX CITY LX CNG BS6.2
A9: MAXX HD 1.3 LX BS6.2
A10: MAXX HD 1.3 VXi AC - BS6.2
A11: MAXX HD 1.7 LX BS6.2
A12: MAXX HD 1.7 LX CBC BS6.2
A13: MAXX HD 1.7 MXi BS6.2
A14: MAXX HD 1.7 VXi AC - BS6.2
... A35: BOL PIK UP FB 1.3T - BS6.2 - PS AC
