Workbook

Sheet Report
D2: Select Vehicle Variant
D3: MAXX CITY 1.3 LX BS6.2
B5: Vehicle Price | C5: Ex-Showroom Price | D5: =IFERROR(VLOOKUP($D$3,Sheet1!$B$2:$Y$45,MATCH(Report!$C5,Sheet1!$B$2:$Y$2,0),0),"") -> 772700 | F5: Sr. | G5: Points
C6: TCS | D6: =IFERROR(VLOOKUP($D$3,Sheet1!$B$2:$Y$45,MATCH(Report!$C6,Sheet1!$B$2:$Y$2,0),0),"") -> 0 | F6: 1 | G6: As per price list insurance is mandatory
C7: Comprehensive + Zero Dep. Insurance | D7: =IFERROR(VLOOKUP($D$3,Sheet1!$B$2:$Y$45,MATCH(Report!$C7,Sheet1!$B$2:$Y$2,0),0),"") -> 46940 | F7: 2 | G7: There is no discount on accessories package
C8: R.T.O. Charges With Hypo. | D8: =IFERROR(VLOOKUP($D$3,Sheet1!$B$2:$Y$45,MATCH(Report!$C8,Sheet1!$B$2:$Y$2,0),0),"") -> 41590 | F8: 3 | G8: Price will remain the same at both showrooms
C9: RSA (Road Side Assistance) For 1 Year | D9: =IFERROR(VLOOKUP($D$3,Sheet1!$B$2:$Y$45,MATCH(Report!$C9,Sheet1!$B$2:$Y$2,0),0),"") -> 1519 | F9: 4 | G9: For vehicles where the accessories package is not free, an accessories package worth ₹12,000 will be mandatory.
C10: SMC Road - Tax (If Applicable) | D10: =IFERROR(VLOOKUP($D$3,Sheet1!$B$2:$Y$45,MATCH(Report!$C10,Sheet1!$B$2:$Y$2,0),0),"") -> 19318 | F10: 5 | G10: NO Additional Payout to be Passed on to DSA - Both PV & CV
C11: MAXI CARE | D11: =IFERROR(VLOOKUP($D$3,Sheet1!$B$2:$Y$45,MATCH(Report!$C11,Sheet1!$B$2:$Y$2,0),0),"") -> 3500 | F11: 6 | G11: NO DSA Sale on Exshowroom
C12: Accessories | D12: =IFERROR(VLOOKUP($D$3,Sheet1!$B$2:$Y$45,MATCH(Report!$C12,Sheet1!$B$2:$Y$2,0),0),"") -> 17000 | F12: 7 | G12: Invoice on full amount
C13: ON ROAD PRICE With SMC Road Tax | D13: =IFERROR(VLOOKUP($D$3,Sheet1!$B$2:$Y$45,MATCH(Report!$C13,Sheet1!$B$2:$Y$2,0),0),"") -> 902567 | F13: 8 | G13: For Camper Model Insurance in house is mandatory and in case of out house Insurance only M&M Consumer offer will be applicable
C14: ON ROAD PRICE Without SMC Road Tax | D14: =IFERROR(VLOOKUP($D$3,Sheet1!$B$2:$Y$45,MATCH(Report!$C14,Sheet1!$B$2:$Y$2,0),0),"") -> 883249 | F14: 9 | G14: Only bulk deals of 10 or more vehicles will be considered outside the cartel
B15: VIN 2026 | C15: Total M&M Scheme with GST (2026) | D15: =IFERROR(VLOOKUP($D$3,Sheet1!$B$2:$Y$45,MATCH(Report!$C15,Sheet1!$B$2:$Y$2,0),0),"") -> 30000 | F15: 10 | G15: Vin's Above 90 Days are open for Discount - Auditor to take Tally Stock on 5th of Every month for >90 Days Stock
C16: VIN 2026 Dealer Offer | D16: =IFERROR(VLOOKUP($D$3,Sheet1!$B$2:$Y$45,MATCH(Report!$C16,Sheet1!$B$2:$Y$2,0),0),"") -> 30K + RSA FREE | F16: 11 | G16: VIN 2024 vehicles are not part of Discount adherance
B17: VIN 2025 | C17: M&M Scheme with GST (2025) | D17: =IFERROR(VLOOKUP($D$3,Sheet1!$B$2:$Y$45,MATCH(Report!$C17,Sheet1!$B$2:$Y$2,0),0),"") -> 38000
C18: Dealer Contribution with GST (2025) | D18: =IFERROR(VLOOKUP($D$3,Sheet1!$B$2:$Y$45,MATCH(Report!$C18,Sheet1!$B$2:$Y$2,0),0),"") -> 10000
C19: Total Scheme with GST (M&M + Dealer) (2025) | D19: =IFERROR(VLOOKUP($D$3,Sheet1!$B$2:$Y$45,MATCH(Report!$C19,Sheet1!$B$2:$Y$2,0),0),"") -> 48000
C20: VIN 2025 Dealer Offer | D20: =IFERROR(VLOOKUP($D$3,Sheet1!$B$2:$Y$45,MATCH(Report!$C20,Sheet1!$B$2:$Y$2,0),0),"") -> 38K + 17K Accessories + RSA FREE
B21: Other Offers | C21: Exchange Bonus | D21: =IFERROR(VLOOKUP($D$3,Sheet1!$B$2:$Y$45,MATCH(Report!$C21,Sheet1!$B$2:$Y$2,0),0),"") -> 35000
C22: Scrappage Bonus | D22: =IFERROR(VLOOKUP($D$3,Sheet1!$B$2:$Y$45,MATCH(Report!$C22,Sheet1!$B$2:$Y$2,0),0),"") -> 45000

Sheet Sheet1
A1: MODEL & VARIANT | C1: VEHICLE PRICE | M1: JAN-2026 VIN 2026 | O1: JAN-2026 VIN 2025 | S1: Other Offers
A2: Model Name | B2: Variant | C2: Ex-Showroom Price | D2: TCS | E2: Comprehensive + Zero Dep. Insurance | F2: R.T.O. Charges With Hypo. | G2: RSA (Road Side Assistance) For 1 Year | H2: SMC Road - Tax (If Applicable) | I2: MAXI CARE | J2: Accessories | K2: ON ROAD PRICE With SMC Road Tax | L2: ON ROAD PRICE Without SMC Road Tax | M2: Total M&M Scheme with GST (2026) | N2: VIN 2026 Dealer Offer | O2: M&M Scheme with GST (2025) | P2: Dealer Contribution with GST (2025) | Q2: Total Scheme with GST (M&M + Dealer) (2025) | R2: VIN 2025 Dealer Offer | S2: Exchange Bonus | T2: Scrappage Bonus
A3: BOL MAXX PUP CITY 1.3 LX | B3: MAXX CITY 1.3 LX BS6.2 | C3: 772700 | D3: 0 | E3: 46940 | F3: 41590 | G3: 1519 | H3: 19318 | I3: 3500 | J3: 17000 | K3: =SUM(C3:J3) -> 902567 | L3: =K3-H3 -> 883249 | M3: 30000 | N3: 30K + RSA FREE | O3: 38000 | P3: 10000 | Q3: 48000 | R3: 38K + 17K Accessories + RSA FREE | S3: 35000 | T3: 45000
A4: BOL MAXX PUP CITY 1.3 LX CBC | B4: MAXX CITY 1.3 LX CBC BS6.2 | C4: 763499 | D4: 0 | E4: 46629 | F4: 41722 | G4: 1519 | H4: 19087 | I4: 3500 | J4: 17000 | K4: =SUM(C4:J4) -> 892956 | L4: =K4-H4 -> 873869 | M4: 30000 | N4: 30K + RSA FREE | O4: 38000 | P4: 10000 | Q4: 48000 | R4: 38K + 17K Accessories + RSA FREE | S4: 35000 | T4: 45000
A5: BOL MAXX PUP CITY 1.3 MXD | B5: MAXX CITY 1.3 MXi BS6.2 | C5: 795600 | D5: 0 | E5: 47715 | F5: 42754 | G5: 1519 | H5: 19890 | I5: 3500 | J5: 17000 | K5: =SUM(C5:J5) -> 927978 | L5: =K5-H5 -> 908088 | M5: 30000 | N5: 30K + RSA FREE | O5: 38000 | P5: 10000 | Q5: 48000 | R5: 38K + 17K Accessories + RSA FREE | S5: 35000 | T5: 45000
A6: BOL MAXX PUP CITY 1.3 SXI AC | B6: MAXX CITY 1.3 SXi AC - BS6.2 | C6: 800199 | D6: 0 | E6: 47869 | F6: 42988 | G6: 1519 | H6: 20005 | I6: 3500 | J6: 17000 | K6: =SUM(C6:J6) -> 933080 | L6: =K6-H6 -> 913075 | M6: 30000 | N6: 30K + RSA FREE | O6: 38000 | P6: 10000 | Q6: 48000 | R6: 38K + 17K Accessories + RSA FREE | S6: 35000 | T6: 45000
A7: BOL MAXX PUP CITY 1.3 VXID AC | B7: MAXX CITY 1.3 VXi AC - BS6.2 | C7: 809400 | D7: 0 | E7: 48178 | F7: 43456 | G7: 1519 | H7: 20235 | I7: 3500 | J7: 17000 | K7: =SUM(C7:J7) -> 943288 | L7: =K7-H7 -> 923053 | M7: 30000 | N7: 30K + RSA FREE | O7: 38000 | P7: 10000 | Q7: 48000 | R7: 38K + 17K Accessories + RSA FREE | S7: 35000 | T7: 45000
A8: BOL MAXX PUP CITY 1.3 VXID | B8: MAXX CITY 1.3 VXi BS6.2 | C8: 791000 | D8: 0 | E8: 47343 | F8: 42520 | G8: 1519 | H8: 19775 | I8: 3500 | J8: 17000 | K8: =SUM(C8:J8) -> 922657 | L8: =K8-H8 -> 902882 | M8: 30000 | N8: 30K + RSA FREE | O8: 38000 | P8: 10000 | Q8: 48000 | R8: 38K + 17K Accessories + RSA FREE | S8: 35000 | T8: 45000
A9: BOL MAXX PUP CITY LX CNG | B9: MAXX CITY LX CNG BS6.2 | C9: 793900 | D9: 0 | E9: 47658 | F9: 42668 | G9: 1519 | H9: 11908 | I9: 3500 | J9: 17000 | K9: =SUM(C9:J9) -> 918153 | L9: =K9-H9 -> 906245 | M9: 65000 | N9: 65K + RSA FREE | O9: 65000 | P9: 10000 | Q9: 75000 | R9: 65K + 17K Accessories + RSA FREE | S9: 35000 | T9: 45000
A10: BOL MAXX PUP HD 1.3 LX | B10: MAXX HD 1.3 LX BS6.2 | C10: 916700 | D10: 0 | E10: 50714 | F10: 48912 | G10: 1519 | H10: 22918 | I10: 3500 | J10: 12000 | K10: =SUM(C10:J10) -> 1056263 | L10: =K10-H10 -> 1033345 | M10: 10000 | N10: MODEL NOT SPECIFIED | O10: 23000 | P10: 5000 | Q10: 28000 | R10: MODEL NOT SPECIFIED | S10: 35000 | T10: 45000
A11: BOL MAXX PUP HD 1.3 VXID AC | B11: MAXX HD 1.3 VXi AC - BS6.2 | C11: 962600 | D11: 0 | E11: 52213 | F11: 51246 | G11: 1519 | H11: 24065 | I11: 3500 | J11: 12000 | K11: =SUM(C11:J11) -> 1107143 | L11: =K11-H11 -> 1083078 | M11: 10000 | N11: MODEL NOT SPECIFIED | O11: 28000 | P11: 5000 | Q11: 33000 | R11: MODEL NOT SPECIFIED | S11: 35000 | T11: 45000
A12: BOL MAXX PUP HD 1.7 LX | B12: MAXX HD 1.7 LX BS6.2 | C12: 926900 | D12: 0 | E12: 51048 | F12: 49781 | G12: 1519 | H12: 23173 | I12: 3500 | J12: 17000 | K12: =SUM(C12:J12) -> 1072921 | L12: =K12-H12 -> 1049748 | M12: 20000 | N12: 20K + RSA FREE | O12: 26000 | P12: 5000 | Q12: 31000 | R12: 26K + 17K Accessories + RSA FREE | S12: 35000 | T12: 45000
A13: BOL MAXX PUP HD 1.7 LX CBC | B13: MAXX HD 1.7 LX CBC BS6.2 | C13: 902000 | D13: 0 | E13: 50233 | F13: 49114 | G13: 1519 | H13: 22550 | I13: 3500 | J13: 17000 | K13: =SUM(C13:J13) -> 1045916 | L13: =K13-H13 -> 1023366 | M13: 20000 | N13: 20K + RSA FREE | O13: 26000 | P13: 5000 | Q13: 31000 | R13: 26K + 17K Accessories + RSA FREE | S13: 35000 | T13: 45000
A14: BOL MAXX PUP HD 1.7 MX | B14: MAXX HD 1.7 MXi BS6.2 | C14: 954400 | D14: 0 | E14: 51947 | F14: 51179 | G14: 1519 | H14: 23860 | I14: 3500 | J14: 17000 | K14: =SUM(C14:J14) -> 1103405 | L14: =K14-H14 -> 1079545 | M14: 10000 | N14: 10K + RSA FREE | O14: 35000 | P14: 5000 | Q14: 40000 | R14: 35K + 17K Accessories + RSA FREE | S14: 35000 | T14: 45000
... A36: BOL PIK UP FB 1.3T - BS6.2 - PS AC | B36: BOL PIK UP FB 1.3T - BS6.2 - PS AC | C36: 985700 | D36: 0 | E36: 52969 | F36: 52420 | G36: 1519 | H36: 24643 | I36: 3500 | J36: 12000 | K36: =SUM(C36:J36) -> 1132751 | L36: =K36-H36 -> 1108108 | M36: 15000 | N36: 15K + RSA FREE | O36: 23000 | P36: 5000 | Q36: 28000 | R36: 23K + 12K Accessories + RSA FREE | S36: 35000 | T36: 45000

Sheet MasterData
A1: Variant | C1: Data Validation Prep. | E1: =VLOOKUP(A3,'[CV Price List D. 09.01.2026.xlsx]Sheet1'!$B$1:$L$35,{2,3,4,5,6,7,8,9,10,11},FALSE)
A2: MAXX CITY 1.3 LX BS6.2 | C2: {=TRANSPOSE(_xlfn._xlws.SORT(_xlfn._xlws.FILTER(Vehicle_Model[Variant],ISNUMBER(SEARCH(Report!D3,Vehicle_Model[Variant])),"Not Found")))} -> MAXX CITY 1.3 LX BS6.2
A3: MAXX CITY 1.3 LX CBC BS6.2
A4: MAXX CITY 1.3 MXi BS6.2
A5: MAXX CITY 1.3 SXi AC - BS6.2
A6: MAXX CITY 1.3 VXi AC - BS6.2
A7: MAXX CITY 1.3 VXi BS6.2
A8: MAXX CITY LX CNG BS6.2
A9: MAXX HD 1.3 LX BS6.2
A10: MAXX HD 1.3 VXi AC - BS6.2
A11: MAXX HD 1.7 LX BS6.2
A12: MAXX HD 1.7 LX CBC BS6.2
A13: MAXX HD 1.7 MXi BS6.2
A14: MAXX HD 1.7 VXi AC - BS6.2
... A35: BOL PIK UP FB 1.3T - BS6.2 - PS AC
